jansevakernel/__init__.py
jansevakernel/__main__.py
jansevakernel/install_kernelspec.py
jansevakernel/kernel.py
jansevakernel-1.0.0.dist-info/LICENSE
jansevakernel-1.0.0.dist-info/METADATA
jansevakernel-1.0.0.dist-info/WHEEL
jansevakernel-1.0.0.dist-info/entry_points.txt
jansevakernel-1.0.0.dist-info/top_level.txt
jansevakernel-1.0.0.dist-info/RECORD
